stratega.cp310-win_amd64.pyd
resources/assets/OutLine.frag
resources/assets/arial.ttf
resources/assets/Entities/Clay.png
resources/assets/Entities/Storage.png
resources/assets/Entities/animals.png
resources/assets/Entities/arrow.png
resources/assets/Entities/barracks.png
resources/assets/Entities/bread.png
resources/assets/Entities/castle.png
resources/assets/Entities/farm.png
resources/assets/Entities/floorRockTall.png
resources/assets/Entities/foundry.png
resources/assets/Entities/gold_chest.png
resources/assets/Entities/guardTower.png
resources/assets/Entities/key.png
resources/assets/Entities/masonry.png
resources/assets/Entities/military.png
resources/assets/Entities/mine.png
resources/assets/Entities/mine2.png
resources/assets/Entities/ore.png
resources/assets/Entities/saw.png
resources/assets/Entities/tower.png
resources/assets/Entities/treeHouse.png
resources/assets/Entities/unit_1.png
resources/assets/Entities/unit_10.png
resources/assets/Entities/unit_2.png
resources/assets/Entities/unit_3.png
resources/assets/Entities/unit_4.png
resources/assets/Entities/unit_5.png
resources/assets/Entities/unit_6.png
resources/assets/Entities/unit_7.png
resources/assets/Entities/unit_8.png
resources/assets/Entities/unit_9.png
resources/assets/Entities/university.png
resources/assets/Entities/wonder.png
resources/assets/Entities/workshop.png
resources/assets/Test2DTopDown/forest.png
resources/assets/Test2DTopDown/notVisible.png
resources/assets/Test2DTopDown/pain.png
resources/assets/Test2DTopDown/plain.png
resources/assets/Test2DTopDown/rock.png
resources/assets/Test2DTopDown/unit_1.png
resources/assets/Test2DTopDown/unit_2.png
resources/assets/Test2DTopDown/unit_3.png
resources/assets/Test2DTopDown/unit_6.png
resources/assets/Test2DTopDown/water.png
resources/assets/Tiles/animals.png
resources/assets/Tiles/clay.png
resources/assets/Tiles/forest.png
resources/assets/Tiles/forestDesert.png
resources/assets/Tiles/gold.png
resources/assets/Tiles/hole.png
Stratega-0.3.1.dist-info/METADATA
Stratega-0.3.1.dist-info/WHEEL
Stratega-0.3.1.dist-info/top_level.txt
Stratega-0.3.1.dist-info/RECORD
