Metadata-Version: 2.1
Name: Stratega
Version: 0.3.1
Summary: Stratega python bindings
Home-page: 
Author: Diego Perez-Liebana, Alexander Dockhorn, Jorge Hurtado Grueso, Dominik Jeurissen
Project-URL: Github, https://github.com/GAIGResearch/Stratega
Project-URL: Community-Discord, https://discord.com/invite/VVj8Y32DPK
Classifier: Topic :: Scientific/Engineering :: Artificial Intelligence
Classifier: Intended Audience :: Science/Research
Classifier: Intended Audience :: Education
Classifier: Natural Language :: English
Classifier: Operating System :: MacOS :: MacOS X
Classifier: Operating System :: POSIX :: Linux
Classifier: Operating System :: Microsoft :: Windows
Classifier: Programming Language :: C++
Classifier: Programming Language :: Python :: 3 :: Only
Classifier: Programming Language :: Python :: 3.7
Classifier: Programming Language :: Python :: 3.8
Classifier: Programming Language :: Python :: 3.9
Classifier: Programming Language :: Python :: 3.10
Classifier: Programming Language :: Python :: Implementation :: CPython
